prompt_enhancer/__init__.py
prompt_enhancer/__main__.py
prompt_enhancer/cli.py
prompt_enhancer/config.py
prompt_enhancer/enhancer.py
prompt_enhancer/utils/__init__.py
prompt_enhancer/utils/config_manager.py
prompt_enhancer/utils/display.py
prompt_enhancer/utils/io.py
prompt_enhancer-1.0.1.dist-info/LICENSE
prompt_enhancer-1.0.1.dist-info/METADATA
prompt_enhancer-1.0.1.dist-info/WHEEL
prompt_enhancer-1.0.1.dist-info/entry_points.txt
prompt_enhancer-1.0.1.dist-info/top_level.txt
prompt_enhancer-1.0.1.dist-info/RECORD
