Metadata-Version: 2.1
Name: prompt-enhancer
Version: 1.0.1
Summary: An AI-powered prompt enhancement tool
Home-page: https://github.com/Moses-chris/terminal-prompt.git
Author: Moses-chris
Author-email: moseschris535@gmail.com
Classifier: Development Status :: 4 - Beta
Classifier: Environment :: Console
Classifier: Intended Audience :: Developers
Classifier: License :: OSI Approved :: MIT License
Classifier: Operating System :: OS Independent
Classifier: Programming Language :: Python :: 3
Classifier: Programming Language :: Python :: 3.7
Classifier: Programming Language :: Python :: 3.8
Classifier: Programming Language :: Python :: 3.9
Classifier: Programming Language :: Python :: 3.10
Classifier: Topic :: Software Development :: Libraries :: Python Modules
Requires-Python: >=3.7
License-File: LICENSE
Requires-Dist: typer
Requires-Dist: groq
Requires-Dist: rich
Requires-Dist: python-dotenv
Requires-Dist: pyperclip
Requires-Dist: prompt_toolkit
Provides-Extra: dev
Requires-Dist: pytest; extra == "dev"
Requires-Dist: black; extra == "dev"
Requires-Dist: isort; extra == "dev"
Requires-Dist: flake8; extra == "dev"
Requires-Dist: build; extra == "dev"
Requires-Dist: twine; extra == "dev"
